[{"id": "BtO5NzdHnpO", "username": "_missirina", "date": "2019-01-29T20:58:18", "hashtags": ["thrifted", "thriftedfashion", "thriftstorefinds", "lordbyronquote", "puremichigan", "winter", "winteroutfit", "themittenstate", "quoteoftheday", "goldenhour", "polarvortex2019", "mamabear", "winterfashion", "nature", "naturelovers", "russiangirlsgram", "poetry", "polarvortex", "naturephotography", "russian"], "imagelinks": ["https://scontent-icn1-1.cdninstagram.com/vp/5464f85ad3990fba75ae3fcfdaf7c82e/5CEC837B/t51.2885-15/e35/50493409_243746379706419_5868579736395418821_n.jpg?_nc_ht=scontent-icn1-1.cdninstagram.com"], "likes": "66", "comments": "2"}, {"id": "BtQ_noTH7c6", "username": "ssuzyyy_", "date": "2019-01-30T16:32:45", "hashtags": [], "imagelinks": ["https://scontent-icn1-1.cdninstagram.com/vp/b655f240abe8fe1f7a45fbc910380bdc/5CF85D23/t51.2885-15/e35/49933401_2319862981558509_1663530775223189144_n.jpg?_nc_ht=scontent-icn1-1.cdninstagram.com"], "likes": "146", "comments": "3"}, {"id": "BtPLuWBg_U4", "username": "rubydrops", "date": "2019-01-29T23:40:02", "hashtags": ["instawinter", "polarvortex2019", "chicwishsweater", "winterwonderland", "snow", "winteroutfit", "shewhowanders", "coldweatherstyle", "chicwish", "winterfashion", "aggielook", "instaoutfit", "virginia", "virginiaisforlovers", "snowfall", "seekmoments", "winter", "snowday", "snowy", "polarvortex", "aggiepresets", "cold", "aggietribe", "chicwishstyle", "coldweather"], "imagelinks": ["https://scontent-icn1-1.cdninstagram.com/vp/699e496edf90d03bc5061c83e79f1988/5CDABC3C/t51.2885-15/e35/49858343_144208003255515_2608007912912988285_n.jpg?_nc_ht=scontent-icn1-1.cdninstagram.com", "https://scontent-icn1-1.cdninstagram.com/vp/c1f171b6db41e024546b911579282224/5CDBC38B/t51.2885-15/e35/50082649_287985385227139_4193737897249127581_n.jpg?_nc_ht=scontent-icn1-1.cdninstagram.com", "https://scontent-icn1-1.cdninstagram.com/vp/76ca198e9cfca773460a19eeaa85248b/5CDC866D/t51.2885-15/e35/49993868_159704805012871_2597901779245020177_n.jpg?_nc_ht=scontent-icn1-1.cdninstagram.com"], "likes": "44", "comments": "2"}, {"id": "BtRXC1rlQ2C", "username": "schierlpeter", "date": "2019-01-30T19:57:26", "hashtags": ["sky_colour", "sunset_colour", "nature_perfektion", "horseslover", "evening_today", "heaven_colours", "sunset_vision", "evening_twilight", "winterfashion", "heaven_vision", "sky_vision", "earth_official", "nature", "sunset_today", "heaven_twilight", "earth_photography", "haflinger", "winter", "heaven_of_love", "sunshine", "silhouetts", "shot_flair", "snow", "naturephotography", "sunset_madness", "horseworld"], "imagelinks": ["https://scontent-icn1-1.cdninstagram.com/vp/b8b1fd85ad83b97905fbafb400874cdc/5CEBAE99/t51.2885-15/e35/50725392_1980346918936507_8154457544663146045_n.jpg?_nc_ht=scontent-icn1-1.cdninstagram.com"], "likes": "55", "comments": "8"}, {"id": "BtPQ8b4H4ok", "username": "blushandcottonshop", "date": "2019-01-30T00:25:39", "hashtags": ["beauty", "fashion", "style", "buymystuff", "instashop", "ootd", "styles", "instagram", "shopping", "onlineboutique", "shopmywardrobe", "thelookforless", "winterfashion", "lifestyle", "fashionblogger", "fashionaddict", "instacloset", "clothes", "designer", "clothing", "instalike", "shopmycloset", "mom", "winter", "shopmystyle", "fashionista", "instamood"], "imagelinks": ["https://scontent-icn1-1.cdninstagram.com/vp/bb370a5692aa5f34ade70e58b52ee33d/5CF1A296/t51.2885-15/e35/49907590_115785886165323_575276943240872302_n.jpg?_nc_ht=scontent-icn1-1.cdninstagram.com", "https://scontent-icn1-1.cdninstagram.com/vp/b31b7e24318c2e4eb1d4dc8203483e72/5CDCB699/t51.2885-15/e35/50559207_578206802606052_8106584451843476883_n.jpg?_nc_ht=scontent-icn1-1.cdninstagram.com"], "likes": "12", "comments": "1"}, {"id": "BtRLwAtlhin", "username": "aeternaphoto", "date": "2019-01-30T18:18:45", "hashtags": ["cozysweater", "wintervibes", "portraitphotography", "bitterrootvalley", "brunettebeauty", "portraiture", "montanaphotographer", "mountainmama", "winterphotoshoot", "greeneyes", "winterfashion", "portrait", "frozenriver", "missoulamontana"], "imagelinks": ["https://scontent-icn1-1.cdninstagram.com/vp/48c3ccf9aefa4648c6dd35a569ca861b/5CF8B31A/t51.2885-15/e35/49956613_940466036162171_7035171799870855819_n.jpg?_nc_ht=scontent-icn1-1.cdninstagram.com"], "likes": "18", "comments": "0"}, {"id": "BtQZvYhHQv6", "username": "sarabeshierfashion", "date": "2019-01-30T11:01:45", "hashtags": ["egypt", "paris", "fashion", "madeinegypt", "black", "blackvelvet", "winter19", "fallfashion", "dubaifashion", "fashionblogger", "fashiondesigner", "follow", "signature", "knitting", "winterfashion", "velvetdress", "sb_girls", "sarabeshierfashion", "cairo", "parisfashion"], "imagelinks": ["https://scontent-icn1-1.cdninstagram.com/vp/8ed16a0f1adba4c8cbfcf7604923efc6/5CEF950A/t51.2885-15/e35/50809203_576660666130735_5928033682284278213_n.jpg?_nc_ht=scontent-icn1-1.cdninstagram.com"], "likes": "426", "comments": "2"}, {"id": "BtPqPqng2eQ", "username": "bombay.balloon", "date": "2019-01-30T04:06:44", "hashtags": ["starlife", "stylefile", "likeforlike", "ootd", "womenswear", "bollywood", "happynewyear", "priyankachoprajonas", "fashion", "indianfashion", "winterwear", "followforfollow", "celebrity", "winterfall", "celebritylife", "priyankachopra", "hello2019", "hindimovies", "summer", "winterfashion", "movies", "fallfashion", "bombayballoon", "menswear"], "imagelinks": ["https://scontent-icn1-1.cdninstagram.com/vp/9d8656af313d4ce694b528ecf3c521e5/5CF070A5/t51.2885-15/e35/49480107_331978860982566_1380082533141451944_n.jpg?_nc_ht=scontent-icn1-1.cdninstagram.com"], "likes": "159", "comments": "1"}, {"id": "BtQZoSxDPwC", "username": "frankieandco_lagos", "date": "2019-01-30T11:00:47", "hashtags": ["humpdaytip", "winterfashion", "fashionable", "snobshots", "kiccessorizeyourlook", "outfitoftheday", "kiccessories", "fashionlover", "seasonalfashion", "jackets", "fallfashion", "fashiongram", "ootd", "businesswomen", "newarrival", "clothes", "fashiontip", "coat", "lookbook"], "imagelinks": ["https://scontent-icn1-1.cdninstagram.com/vp/d91d84c79278f89c85f5d4b2d686ae65/5CEC9B10/t51.2885-15/fr/e15/s1080x1080/50014839_1143971889104419_8224860271728606961_n.jpg?_nc_ht=scontent-icn1-1.cdninstagram.com"], "likes": "33", "comments": "3"}, {"id": "BtL4iexHE0k", "username": "zh7858", "date": "2019-01-28T16:54:40", "hashtags": ["makeup", "fashionista", "white", "man", "girl", "fashion", "weddingdress", "model", "passion", "fashiondiaries", "winterfashion", "styleblogger", "fashionaddict", "stylish", "instafashion", "followme", "fashionstyle", "flowers", "hypebeast", "style", "fashionphotography", "fashionblogger", "instagood", "fashionable", "ootd", "fashiondesigner", "happy", "art", "cool", "instalike"], "imagelinks": ["https://scontent-icn1-1.cdninstagram.com/vp/e8f705075cf567a33ad68adf945b63c4/5CF26DB0/t51.2885-15/e35/49720053_435353500552303_4962733506304164674_n.jpg?_nc_ht=scontent-icn1-1.cdninstagram.com"], "likes": "67", "comments": "12"}, {"id": "BtRxOsUli8W", "username": "sals_eg", "date": "2019-01-30T23:46:15", "hashtags": ["winterfashion", "positivevibes", "wintertoptrends", "ootd", "wardawintercollection18", "fashionwindows", "layeriton", "eleganceisanattitude", "wintershopping", "sals_eg", "winterstreetstyle", "wintertrends", "fw18"], "imagelinks": ["https://scontent-icn1-1.cdninstagram.com/vp/9fb441fab7ebb086d5107b2f8be538ab/5CFC6331/t51.2885-15/e35/50076764_2221730944545090_4231220322871342132_n.jpg?_nc_ht=scontent-icn1-1.cdninstagram.com"], "likes": "22", "comments": "1"}, {"id": "BtPi-mPhgYg", "username": "jen_wonders", "date": "", "hashtags": [], "imagelinks": ["https://scontent-icn1-1.cdninstagram.com/vp/4029dc8f2d0dc0eae24b168a90d18952/5D001CA5/t51.2885-15/e35/50254800_2256819714597988_447490141988941841_n.jpg?_nc_ht=scontent-icn1-1.cdninstagram.com"], "likes": "0", "comments": "0"}, {"id": "BtPJn0an61f", "username": "mio_kurihara", "date": "", "hashtags": ["\u30d5\u30a9\u30ed\u30fc\u30d0\u30c3\u30af", "whitesneakers", "beachtime", "\u767d\u30b9\u30cb\u30fc\u30ab\u30fc", "reebokclassic", "wednesday", "wear", "reebok", "sneaker", "outfit", "pantscode", "\u6d5c\u8fba", "\u30ea\u30fc\u30dc\u30c3\u30af", "\u30d5\u30ea\u30fc\u30af\u30b9\u30b9\u30c8\u30a2", "\u6d77\u30b3\u30fc", "\u7802\u6d5c", "ottd", "winterfashion", "\u30d0\u30f3\u30b0\u30eb", "\u3044\u3044\u306d\u8fd4\u3057\u307e\u3059", "\u30c1\u30a7\u30c3\u30af\u30d1\u30f3\u30c4", "\u3044\u3044\u306d\u8fd4\u3057", "freaksstore", "beach", "beachlife", "\u30d5\u30a9\u30ed\u30fc\u3057\u307e\u3059", "\u79c1\u670d", "\u30d3\u30fc\u30c1\u30b3\u30fc\u30c7", "\u51ac\u306e\u6d77"], "imagelinks": ["https://scontent-icn1-1.cdninstagram.com/vp/ed54351f67d247520958fb1101bb90a4/5CF599D9/t51.2885-15/e35/50138732_745140255866299_3078558436431917647_n.jpg?_nc_ht=scontent-icn1-1.cdninstagram.com"], "likes": "0", "comments": "0"}, {"id": "BtPuGErhVhq", "username": "okanaganmomstyle", "date": "2019-01-30T04:40:22", "hashtags": ["wintertrends", "fashion", "cozyoutfit", "ootdfashion", "winterfashion", "kelownanow", "sweaterseason", "okanaganliving", "shoplocal", "okanagan", "babessupportingbabes", "okanaganmomstyle", "dailylook", "kelowna", "momlife", "ootd", "tailgateparty"], "imagelinks": ["https://scontent-icn1-1.cdninstagram.com/vp/169b844929a629aa6d36f12693eec697/5CF8BA0D/t51.2885-15/e35/51550016_2147641225546135_1662225457658434465_n.jpg?_nc_ht=scontent-icn1-1.cdninstagram.com"], "likes": "67", "comments": "4"}, {"id": "BtRoDiBnlUo", "username": "thestyledgem", "date": "2019-01-30T22:26:05", "hashtags": ["ootdmagazine", "styleblogger", "casualootd", "fashion", "lackofcolor", "iweargarage", "fashionblogger", "weekendlook", "thestyledgem", "fashioninspo", "outfitinspo", "fashionblog", "casualstyle", "winterfashion", "style", "ootd", "outfitpost", "personalstyleblogger", "winterstyle"], "imagelinks": ["https://scontent-icn1-1.cdninstagram.com/vp/e5180b43a474a36101f79ac66128fd7d/5CE1FAE5/t51.2885-15/e35/51765215_549769605539543_8610553648981015585_n.jpg?_nc_ht=scontent-icn1-1.cdninstagram.com"], "likes": "51", "comments": "5"}, {"id": "BtOv47_lWUp", "username": "melvassili", "date": "2019-01-29T19:36:49", "hashtags": ["dressingup", "rubyring", "winterfashion", "goldjewelry", "winteroutfit", "darkred", "coldweatherfashion", "wintercolors", "velourdress", "fluffyearmuffs", "zirconiaring", "earmuffs"], "imagelinks": ["https://scontent-icn1-1.cdninstagram.com/vp/996a7959014b9b633859af61849ffb49/5CF1D263/t51.2885-15/e35/50863782_368158580686704_4486575269895515656_n.jpg?_nc_ht=scontent-icn1-1.cdninstagram.com"], "likes": "67", "comments": "0"}, {"id": "BtRWycPnm6f", "username": "collection_su", "date": "2019-01-30T19:55:12", "hashtags": ["\u0645\u0644\u0627\u0628\u0633", "todaysoutfit", "instaonlines", "instashop", "womenfashion", "outfitpost", "newstyle", "collection", "ootdmagazi", "coldweather", "lookoftneday", "womenswear", "\u0633\u0648\u0627\u0631\u064a\u0647", "onlineshopp", "\u062d\u062c\u0627\u0628\u0627\u062a", "\u0645\u062d\u062c\u0628\u0627\u062a", "outfit", "fallstyle", "styleoftheday", "fashionblog", "fashionaddict", "winterclothes", "fashiongram", "\u0639\u0627\u0644\u0645", "stylish", "fashionista", "\u062d\u062c\u0627\u0628", "\u0643\u0627\u062c\u0648\u0627\u0644", "winterfashion"], "imagelinks": ["https://scontent-icn1-1.cdninstagram.com/vp/d5d144e5e5a9779076f23b26c276d1b3/5CF5321C/t51.2885-15/e35/49907572_530160747469763_3680668450125956465_n.jpg?_nc_ht=scontent-icn1-1.cdninstagram.com"], "likes": "12", "comments": "0"}, {"id": "BsKZ-imHNLO", "username": "", "date": "2019-01-03T06:36:59", "hashtags": ["indianoutfits", "indianfashion", "indiancouture", "winterfashion", "winterstylefiles", "winterstylefile", "winterstyle", "indianfashionblogger", "indianoutfit", "winterstyles", "flatlayoftheday"], "imagelinks": ["https://scontent-icn1-1.cdninstagram.com/vp/53f9a20150b871343afd95799ec1da03/5CDB4CE6/t51.2885-15/e35/45684057_2071864836367565_116425877884817761_n.jpg?_nc_ht=scontent-icn1-1.cdninstagram.com", "https://scontent-icn1-1.cdninstagram.com/vp/e78952e32712d16d38a0a05146038ffc/5CE7C6D4/t51.2885-15/e35/47692407_126520638378699_447698164442725463_n.jpg?_nc_ht=scontent-icn1-1.cdninstagram.com", "https://scontent-icn1-1.cdninstagram.com/vp/59e82be18c687b7f73aa87b01a6bf8c3/5CFBD46A/t51.2885-15/e35/47582507_2131762723547639_8319320485170287080_n.jpg?_nc_ht=scontent-icn1-1.cdninstagram.com"], "likes": "81", "comments": "1"}, {"id": "BtRBeCMBfzw", "username": "shopurbanposh", "date": "", "hashtags": ["nyc", "instagrammodel", "stlouis", "florida", "cuties", "winterfashion", "boutique", "atlanta", "newyork", "lasvegas", "stl", "beauty", "heart", "losangeles", "blog", "blogger", "cuteoutfit", "january", "fashion", "atl", "gorgeous", "winter", "pretty", "cutevideos"], "imagelinks": ["https://scontent-icn1-1.cdninstagram.com/vp/56a3f5830026cb86739ab2a180a64942/5CE3C514/t51.2885-15/e35/p1080x1080/49993865_400780167341486_8729808578777614917_n.jpg?_nc_ht=scontent-icn1-1.cdninstagram.com", "https://scontent-icn1-1.cdninstagram.com/vp/2ebbe97d060d0f16f19069568d95c80d/5CEA338C/t51.2885-15/e35/p1080x1080/49956539_314824419160906_2156040563344456277_n.jpg?_nc_ht=scontent-icn1-1.cdninstagram.com", "https://scontent-icn1-1.cdninstagram.com/vp/34aa30da6d18fc1b3f21a22c5e65ee78/5CF3B8D5/t51.2885-15/e35/p1080x1080/50547090_300807553910603_2255497136405279530_n.jpg?_nc_ht=scontent-icn1-1.cdninstagram.com"], "likes": "0", "comments": "0"}, {"id": "BtQgtVKFPtd", "username": "thegelibabyway", "date": "2019-01-30T12:02:38", "hashtags": ["babyboy", "myboy", "trendyboys", "stylefirst", "littleboysclothes", "boys", "boysclothes", "kickers", "kidswithstyle", "dadswithlads", "littleboys", "trendylittleman", "stylishkids", "mumswithsons", "follow", "winterfashion", "followus", "stellamccartney", "followformore", "designerwear"], "imagelinks": ["https://scontent-icn1-1.cdninstagram.com/vp/419cced8120728863e13063359fa812b/5CEB5988/t51.2885-15/e35/50921871_325068938103936_1126295937628695894_n.jpg?_nc_ht=scontent-icn1-1.cdninstagram.com"], "likes": "9", "comments": "0"}, {"id": "BtSGeBfnVXZ", "username": "a_southerndrawl", "date": "2019-01-31T02:51:50", "hashtags": ["fairisle", "cozyoutfit", "winteroutfit", "tasselsweater", "winterfashion", "cozystyle", "polarvortex", "tassels", "liketkit", "cozyvibes", "winterstyle"], "imagelinks": ["https://scontent-icn1-1.cdninstagram.com/vp/eb2a0986a44a90f5656416153e328b78/5CE1E28E/t51.2885-15/e35/50076014_927346067656298_6596792591847515563_n.jpg?_nc_ht=scontent-icn1-1.cdninstagram.com"], "likes": "1512", "comments": "512Likes38"}, {"id": "BtQSrM4ARhK", "username": "pinuspinas", "date": "2019-01-30T10:00:01", "hashtags": ["winter", "capellibelli", "dreams", "cut", "likeforfollow", "lostileinprimopiano", "vivaleemozioniforti", "buongiorno", "bellezza", "fashion", "felicit\u00e0", "hair", "model", "passion", "diamonds", "look", "libertas", "positivethinking", "crediinte", "style", "fidatidite", "winterfashion", "hairstyle", "professionals", "colour"], "imagelinks": ["https://scontent-icn1-1.cdninstagram.com/vp/7cd31ffbf9aa0f17eb862fd4f430e942/5CE780AB/t51.2885-15/e35/50603805_1277390035735036_4050108774611193780_n.jpg?_nc_ht=scontent-icn1-1.cdninstagram.com"], "likes": "20", "comments": "4"}, {"id": "BtO4tzWl_y1", "username": "ghosts.streetwear", "date": "2019-01-29T20:53:56", "hashtags": ["fitsonpoint", "yeezy", "streetwearsource", "fashionfuckery", "streetwearaddicted", "adidas", "nikeairforce1", "rafsimons", "streetwearco", "classyvision", "acoldwall", "classyoutfit", "cozystreetwear", "nike", "smartstreetwear", "winterfashion", "photooftheday", "cvshed", "viral", "streetwearbrands", "hsstyle", "streetweardaily", "streetwearmalaysia", "explore", "denmark", "streetwearph", "boo", "ootd", "london"], "imagelinks": ["https://scontent-icn1-1.cdninstagram.com/vp/b7e0dedce4fe470767f5bb7ab84078c3/5CEC937B/t51.2885-15/e35/49906886_343121573195846_8766290936856963032_n.jpg?_nc_ht=scontent-icn1-1.cdninstagram.com"], "likes": "65", "comments": "2"}, {"id": "BtSJP3rFUHX", "username": "breemoskowitz", "date": "2019-01-31T03:16:07", "hashtags": ["winterfashion", "lookbook", "loveit", "lookoftheday", "currentlywearing", "bows", "mirrorselfie", "pinklips", "diamonds", "zara", "ootd", "whatiwore", "brunetteambition", "9to5chic", "stripes", "newin", "instafashion", "ruffles", "fashiongram", "chanel", "lashes", "collaredshirt", "blingbling", "nyc", "confessionsofashopaholic", "brows"], "imagelinks": ["https://scontent-icn1-1.cdninstagram.com/vp/6bff4112314a3449e1a4fc1417546d45/5CDADEA8/t51.2885-15/e35/50592110_761409810886246_807700610502646353_n.jpg?_nc_ht=scontent-icn1-1.cdninstagram.com"], "likes": "30", "comments": "3"}, {"id": "BkdtKuWhNq5", "username": "danish__wakeel", "date": "", "hashtags": ["mustached", "streetstyleinspo", "styleinspo", "gqstyle", "sartorial", "trackpants", "pakistanicelebrity", "alexandermcqueen", "londonfashionmodels", "maleactor", "goodvibes", "ootdfashion", "fashionmodel", "newface", "ootd", "pakistanicelebrities", "gentlemen", "madeinpakistan", "luxury", "winterfashion", "actorinthemaking", "fashionista", "menwithstreetstyle", "fashionpakistan", "dappermen", "malemodel", "instantlollywood", "fashiongram", "gymfitness", "fashiontoday"], "imagelinks": ["https://scontent-icn1-1.cdninstagram.com/vp/efd0f6443e366f2a7569cecf7e8a4295/5CF0DD68/t51.2885-15/e35/35575540_258096058273015_3628012012266586112_n.jpg?_nc_ht=scontent-icn1-1.cdninstagram.com"], "likes": "0", "comments": "0"}, {"id": "BtQwpqhF7nO", "username": "schierlpeter", "date": "2019-01-30T14:21:57", "hashtags": ["snowfall", "naturephotography", "snowland", "snow", "snowphotography", "nature", "winterfashion", "naturegallerie", "letzte", "snowsports", "winter_landscape", "landscape_shot", "awesome", "snowshoe", "wei\u00dfe_pracht", "landscape", "austria_landscapes", "niceshot", "snowflake", "white_nature", "tirol", "nature_perfektion", "snowman", "love_dutch_nature", "austria", "sunshine", "weatherphotos", "winterwonderland"], "imagelinks": ["https://scontent-icn1-1.cdninstagram.com/vp/d96300b2a8ca351572f42578346d3dff/5CED2273/t51.2885-15/e35/49759356_2032827613451951_6699568276347673966_n.jpg?_nc_ht=scontent-icn1-1.cdninstagram.com"], "likes": "46", "comments": "0"}, {"id": "BtPbtX2FFgX", "username": "rfdreamergirl", "date": "2019-01-30T01:59:43", "hashtags": ["winter", "style", "antiaging", "fabulashes", "fashion", "rf", "beauty", "winterfashion", "styleinspo", "lashes"], "imagelinks": ["https://scontent-icn1-1.cdninstagram.com/vp/8283d228beda8e60a7e1dad8b6fcfaf9/5CFB1F91/t51.2885-15/e35/50043824_606376723166682_3674842425389229991_n.jpg?_nc_ht=scontent-icn1-1.cdninstagram.com"], "likes": "16", "comments": "2"}, {"id": "5Vl65_FXUc", "username": "ddcowclothingco", "date": "2015-07-20T00:11:53", "hashtags": ["hats", "photographer", "ootd", "fallstyle", "style", "mensstyle", "fallfashion", "photography", "monterrey", "winterfashion", "mexico", "fedora", "fashionphotography", "hat", "womensstyle", "autumn", "repost", "womensfashion", "trucker", "mensfashion", "winter", "ddcow", "fall", "animal", "winsterstyle", "fashion"], "imagelinks": ["https://scontent-icn1-1.cdninstagram.com/vp/c3747aa8e9d5e09f87f5470a0c6b444d/5CF476A8/t51.2885-15/e35/11420726_461314297389658_1212816839_n.jpg?_nc_ht=scontent-icn1-1.cdninstagram.com"], "likes": "71", "comments": "3"}, {"id": "BtQmKvGn0Hn", "username": "hienmac.cestsi", "date": "2019-01-30T12:50:21", "hashtags": ["ootd", "winter2018", "hienmaccestsi", "koreanstyle", "accessories", "ootdvietnam", "hienmacaccessories", "winterfashion"], "imagelinks": ["https://scontent-icn1-1.cdninstagram.com/vp/e743f20090f4a8adae34c4dc6f92a434/5D017583/t51.2885-15/e35/49770265_500437980360376_5878586440648635678_n.jpg?_nc_ht=scontent-icn1-1.cdninstagram.com", "https://scontent-icn1-1.cdninstagram.com/vp/6e2534d2c874b1e77de42c794b809142/5CFBA567/t51.2885-15/e35/50485610_2227982287416507_173621364389625959_n.jpg?_nc_ht=scontent-icn1-1.cdninstagram.com"], "likes": "6", "comments": "0"}, {"id": "BtQ3iwdlNG5", "username": "totallyeffinrad", "date": "2019-01-30T15:22:10", "hashtags": ["sweaterweather", "leatherboots", "madewell", "skinnyjeans", "basicootd", "booties", "instame", "fashion", "instaootd", "madewelljeans", "fashionobsessed", "frye", "winterootd", "highwaistedjeans", "fryeboots", "winteroutfit", "coldweatherfashion", "ootdfashion", "simpleootd", "basicfashion", "ootdstyle", "instafashion", "ootd", "everydaymadewell", "instagood", "instadaily", "instafun", "winterfashion", "bangs", "cuteoutfit"], "imagelinks": ["https://scontent-icn1-1.cdninstagram.com/vp/2761eeba9c807b09bdfc0536bc1c356f/5CE4AFE1/t51.2885-15/e35/50646846_294504008090567_6602356908318835307_n.jpg?_nc_ht=scontent-icn1-1.cdninstagram.com"], "likes": "49", "comments": "8"}, {"id": "BtRVvSDlWl9", "username": "gregshaberdashery", "date": "2019-01-30T19:46:02", "hashtags": ["topcoat", "baltimoreweather", "gregshaberdashery", "smallblackbusinessowner", "coatseason", "coatmaker", "gqstyle", "keepwarm", "baltimore", "haberdashery", "haberdashed", "mensapparel", "mensfashion", "tailor", "dopefashion", "baltimoreshop", "gqgent", "dappergent", "winterfashion"], "imagelinks": ["https://scontent-icn1-1.cdninstagram.com/vp/929c7cfb02213a4b339c72f1f3878349/5CECA48D/t51.2885-15/e35/50840167_114334916323712_7062115898629540987_n.jpg?_nc_ht=scontent-icn1-1.cdninstagram.com"], "likes": "60", "comments": "1"}, {"id": "BtPNcfnFkUd", "username": "urboutiquek", "date": "2019-01-29T23:55:05", "hashtags": ["upscaleresale", "lboutiquek", "ruffle", "beverlydrive", "openfront", "layering", "looseknit", "winterfashion", "multicolor", "knit", "vest", "sweater", "sweatervest", "sweaterweather"], "imagelinks": ["https://scontent-icn1-1.cdninstagram.com/vp/7826bf43f3fe75ca60edb16782dea18d/5CF5E225/t51.2885-15/fr/e15/s1080x1080/50103996_2036474313110910_36216622594868778_n.jpg?_nc_ht=scontent-icn1-1.cdninstagram.com"], "likes": "3", "comments": "0"}, {"id": "BtR6nQ6HnAq", "username": "", "date": "2019-01-31T01:08:15", "hashtags": ["vvposh", "loveyourself", "beautiful", "goodtimes", "womenowned", "sweaters", "funtimes", "boutique", "girltime", "shoplocal", "winterfashion"], "imagelinks": ["https://scontent-icn1-1.cdninstagram.com/vp/eb15cc73c28ce7baeaf4f2a29d29f109/5CF6E191/t51.2885-15/e35/50545418_794630104232781_9028919911998636790_n.jpg?_nc_ht=scontent-icn1-1.cdninstagram.com"], "likes": "37", "comments": "0"}, {"id": "BtR4V_TnvqD", "username": "sierra.oetjen", "date": "2019-01-31T00:48:24", "hashtags": ["momlife", "bow", "coldweather", "cold", "kidsboots", "mommy", "kidsfashion", "cardigan", "kids", "littleblackdress", "2019", "tutu", "daughter", "overkneeboots", "winterweather", "hairbows", "blackdress", "mommyandme", "littleone", "winterfashion"], "imagelinks": ["https://scontent-icn1-1.cdninstagram.com/vp/71bbd39cb95de66b8e8e9fc3080270de/5D008D21/t51.2885-15/e35/49858065_2280016442276773_7885954799643428924_n.jpg?_nc_ht=scontent-icn1-1.cdninstagram.com"], "likes": "56", "comments": "2"}, {"id": "BtRhxjBHsD4", "username": "", "date": "2019-01-30T21:31:12", "hashtags": ["yorkshire", "cobblestone", "theshambles", "bnwphotography", "silverlinings", "streetlife", "cobblestonestreets", "streetphotographer", "winterfashion", "bnw_greatshots", "alleyway", "york", "streetphotography", "shambles", "blackandwhite", "silverlining", "streetphoto", "bnw"], "imagelinks": ["https://scontent-icn1-1.cdninstagram.com/vp/19da037e4ea69a78e830e444a7c51473/5CDC0015/t51.2885-15/e35/50491380_2347198161986425_6700267762288293230_n.jpg?_nc_ht=scontent-icn1-1.cdninstagram.com"], "likes": "26", "comments": "1"}, {"id": "BtQtVgTnN6N", "username": "mallshopping912", "date": "2019-01-30T13:52:59", "hashtags": ["luxurylife", "winterfashion", "orderonline", "onlineshopping", "beunique_with_classic_accessories", "brand", "brandclothing", "followme", "fashiondesigner", "furfashion", "onlinestore", "slaying", "luxurylifestyle", "besexy", "fashion", "bloggerstyle", "fashionaddict", "designer", "bloggers", "onlinefashion", "brandy", "shippingworldwide", "ladyluxury", "fashionnova", "followersfree", "slayinbeauties_", "classy", "classyfashion", "onlineshoppingmall", "befashion"], "imagelinks": ["https://scontent-icn1-1.cdninstagram.com/vp/792f46ac1a3a91ca8374fd9f91a28aa8/5CEFD00F/t51.2885-15/e35/49858759_2270670073256764_4708532440448714004_n.jpg?_nc_ht=scontent-icn1-1.cdninstagram.com", "https://scontent-icn1-1.cdninstagram.com/vp/dc59e25c28e612a80a4313967e8295aa/5CDB26FE/t51.2885-15/e35/49845477_351648555424767_1310239032831985669_n.jpg?_nc_ht=scontent-icn1-1.cdninstagram.com"], "likes": "10", "comments": "0"}, {"id": "BtQmVt9FBDr", "username": "reet_photograpy", "date": "2019-01-30T12:51:51", "hashtags": ["photo", "style", "shinomotoakihocosplay", "edit", "s", "hundsome_boy", "indian", "winterfashion", "look"], "imagelinks": ["https://scontent-icn1-1.cdninstagram.com/vp/14ddd567983b25b56c7872ef645fa233/5CE702FE/t51.2885-15/e35/50130282_404577633627680_1344951655512109411_n.jpg?_nc_ht=scontent-icn1-1.cdninstagram.com"], "likes": "28", "comments": "2"}, {"id": "Bo2WIObHJl2", "username": "rkhatsknits", "date": "2018-10-12T22:04:22", "hashtags": ["model", "winterfashion", "like", "art", "fashion", "winter", "love", "winterstyle", "style", "instagood", "dog", "fashionblogger", "instagram", "travel", "ootd", "men", "beauty", "shopping", "winteroutfit", "snow", "bhfyp", "streetstyle", "mensfashion", "winterwonderland", "follow", "photography", "me", "instafashion", "photooftheday", "christmas"], "imagelinks": ["https://scontent-icn1-1.cdninstagram.com/vp/a8b1cd9a40a490f80b656a55cc4db01d/5CE0489F/t51.2885-15/e35/42345019_1913910178701215_6088394645622943423_n.jpg?_nc_ht=scontent-icn1-1.cdninstagram.com"], "likes": "108", "comments": "5"}, {"id": "BtO9I9sAZKZ", "username": "veganlifestyleblogger", "date": "2019-01-29T21:32:36", "hashtags": [], "imagelinks": ["https://scontent-icn1-1.cdninstagram.com/vp/a8ab7ae53d43f2dbf14436aeafd84de1/5D004929/t51.2885-15/e35/p1080x1080/50284116_1846714845456279_5411229912522599536_n.jpg?_nc_ht=scontent-icn1-1.cdninstagram.com", "https://scontent-icn1-1.cdninstagram.com/vp/b812e2213df9205727d5333f0651f934/5CEC4709/t51.2885-15/e35/p1080x1080/50804099_152015475792055_8545041925118605082_n.jpg?_nc_ht=scontent-icn1-1.cdninstagram.com"], "likes": "85", "comments": "7"}, {"id": "Bs0EH9Bhf8F", "username": "cristina_gruianu", "date": "2019-01-19T10:54:08", "hashtags": ["winterfashion", "fashion", "nature", "winter", "shooting"], "imagelinks": ["https://scontent-icn1-1.cdninstagram.com/vp/0a46c3c336563c97d274b9a7489819ab/5CF71E92/t51.2885-15/e35/49319638_112426673172000_4894351209218931036_n.jpg?_nc_ht=scontent-icn1-1.cdninstagram.com"], "likes": "80", "comments": "0"}, {"id": "BtR1KSclCfm", "username": "tangelgoddess", "date": "2019-01-31T00:20:36", "hashtags": ["winterfashion", "polarvortex", "layersonlayers", "babyitscoldoutside"], "imagelinks": ["https://scontent-icn1-1.cdninstagram.com/vp/27c490de96a5c7578718c88ff355cd7c/5CE2B9F2/t51.2885-15/e35/49956630_402792160474199_8853563197625738475_n.jpg?_nc_ht=scontent-icn1-1.cdninstagram.com", "https://scontent-icn1-1.cdninstagram.com/vp/c1fb9f79f7cc2966398bae31c243ed6f/5CF9DD13/t51.2885-15/e35/50654767_288055408448998_1557364300881371897_n.jpg?_nc_ht=scontent-icn1-1.cdninstagram.com", "https://scontent-icn1-1.cdninstagram.com/vp/083aabf596789fa14204e4c3e1c6a6e7/5CDB4FB8/t51.2885-15/e35/50020172_2220143298198964_4189133725574512517_n.jpg?_nc_ht=scontent-icn1-1.cdninstagram.com", "https://scontent-icn1-1.cdninstagram.com/vp/ec38b5bdbeed4c7657ff924ca4b1c2d3/5CF22FB2/t51.2885-15/e35/49997671_2021402784821840_7521847050801568748_n.jpg?_nc_ht=scontent-icn1-1.cdninstagram.com"], "likes": "12", "comments": "0"}, {"id": "BtQimvCgCUv", "username": "bloggers_pg_", "date": "", "hashtags": ["fashionshoot", "dresses", "chic", "whowhatwear", "pink", "luxury", "icon", "girl", "love", "prettylittleiiinspo", "influencer", "wearitloveit", "fashionperfection", "momentofchic", "stylegoals", "instastyle", "americanstyle", "black", "glasses", "streetstyle", "fashionistas", "fashionstyle", "stylish", "outfit", "styleblogger", "lookoftheday", "ootdmagazine", "winterfashion", "lifestyle", "streetwear"], "imagelinks": ["https://scontent-icn1-1.cdninstagram.com/vp/3119d3a7c1b704d2ed43438b75db52b7/5CF27E71/t51.2885-15/e35/50499612_1984830844949527_5590818356434624380_n.jpg?_nc_ht=scontent-icn1-1.cdninstagram.com"], "likes": "0", "comments": "0"}, {"id": "BtRdfVeh7aB", "username": "ankitanicca", "date": "2019-01-30T20:53:45", "hashtags": ["drapes", "winterfashion", "winterwear", "sareesaga", "weddingseason", "tanchoi", "winternight", "tanchoisilk", "ootd", "sareelove", "weddingdress"], "imagelinks": ["https://scontent-icn1-1.cdninstagram.com/vp/f3df9bb0fc5016bfe81242d9ae5bb63f/5CDEFCF1/t51.2885-15/e35/51140478_970978356441998_1194528589311469237_n.jpg?_nc_ht=scontent-icn1-1.cdninstagram.com", "https://scontent-icn1-1.cdninstagram.com/vp/ccce7d6dbf6929d319e950551abaf347/5CF50726/t51.2885-15/e35/49933777_2276276652402836_6162102357732141325_n.jpg?_nc_ht=scontent-icn1-1.cdninstagram.com"], "likes": "75", "comments": "2"}, {"id": "BtQ08FmFOkc", "username": "fufubaby121", "date": "2019-01-30T15:05:55", "hashtags": [], "imagelinks": ["https://scontent-icn1-1.cdninstagram.com/vp/e09f32b6fd307012240d8b84897a13f3/5C55979F/t51.2885-15/e15/49933600_1042846489252731_3463568598121973539_n.jpg?_nc_ht=scontent-icn1-1.cdninstagram.com"], "likes": "14", "comments": "0"}, {"id": "BtREdSdApu-", "username": "tinyintrigues", "date": "2019-01-30T17:15:01", "hashtags": ["vintageinspired", "littleantiqueme", "1940slibrarian", "pinupfashion", "winterfashion", "1940sfashion", "oldfashionnotoldfashioned", "1940s", "vintagestyle", "truevintagejewelry", "ootd", "longpencilskirt", "1940sstyle", "ootdstyle", "ootddaily", "vintagefashion", "ootddetails", "ootdfashion"], "imagelinks": ["https://scontent-icn1-1.cdninstagram.com/vp/fcceae98762ea8eabfb431f6d153cff6/5D00631D/t51.2885-15/e35/50338253_325892151358874_4208202458456749194_n.jpg?_nc_ht=scontent-icn1-1.cdninstagram.com"], "likes": "109", "comments": "5"}, {"id": "BtRmpqUFG2I", "username": "fashioninspirationmodest", "date": "2019-01-30T22:13:48", "hashtags": ["newyork", "homedecor", "modesty", "beauty", "inspirationalquotes", "babiesofinstagram", "mondays", "fashion", "winterfashion2019", "homesweethome", "diy", "winterfashion", "quotes", "bloggerstyle", "thatscute", "cold", "work", "coldweather", "blogger", "kidsfashion", "pretty", "modestfashion", "loveyourself", "letsstayhome", "losangeles", "lovegod", "homestyledecor", "hip", "lovely"], "imagelinks": ["https://scontent-icn1-1.cdninstagram.com/vp/e7589f5c34cb84fadc590b5a532e6b0d/5CE869E9/t51.2885-15/e35/50128967_402895570478195_3574731196755618410_n.jpg?_nc_ht=scontent-icn1-1.cdninstagram.com"], "likes": "13", "comments": "3"}, {"id": "BtP1SC9AhZ1", "username": "savoir.accoutre", "date": "2019-01-30T05:43:10", "hashtags": ["nonperishable", "longsleeve", "linkinbio", "blackshirt", "savoir", "winterfashion", "boys", "shirt"], "imagelinks": ["https://scontent-icn1-1.cdninstagram.com/vp/24e04487de893d5fb7b9692a5b21855f/5CE84FA4/t51.2885-15/e35/50745861_639606746442553_1128275768929912094_n.jpg?_nc_ht=scontent-icn1-1.cdninstagram.com", "https://scontent-icn1-1.cdninstagram.com/vp/21617f209b4496179419c4efddb264b6/5CEE9D09/t51.2885-15/e35/51193708_1211116935707415_5490426828082201819_n.jpg?_nc_ht=scontent-icn1-1.cdninstagram.com", "https://scontent-icn1-1.cdninstagram.com/vp/f71b21d03bc5be2b351d49c154a554f6/5CF85EE7/t51.2885-15/e35/49858526_1071083689743628_5478494315026235063_n.jpg?_nc_ht=scontent-icn1-1.cdninstagram.com"], "likes": "2", "comments": "0"}, {"id": "BtPVckcl7tY", "username": "_happygocurly_", "date": "2019-01-30T01:04:59", "hashtags": ["ltkstyletip", "liketkit", "ltkunder50", "ltkunder100", "ltkcurves", "ltksalealert"], "imagelinks": ["https://scontent-icn1-1.cdninstagram.com/vp/9ce7258ecf47742c80db25d232e01638/5CDE35F8/t51.2885-15/e35/49833375_545105242660416_8389489971786145029_n.jpg?_nc_ht=scontent-icn1-1.cdninstagram.com"], "likes": "394", "comments": "76"}, {"id": "BtQnYBHB8j_", "username": "syncabrera", "date": "2019-01-30T13:00:54", "hashtags": ["winterstyle", "syncabrera", "winterfashion", "washingtondc", "brotherlylove"], "imagelinks": ["https://scontent-icn1-1.cdninstagram.com/vp/c34e36611348b278e1fd1f1045c63128/5CF89C11/t51.2885-15/e35/50083430_2089477491143297_606021591700882492_n.jpg?_nc_ht=scontent-icn1-1.cdninstagram.com"], "likes": "19", "comments": "1"}, {"id": "BtQkKaqF_-y", "username": "zgstudio_essentials", "date": "2019-01-30T12:32:49", "hashtags": ["thecoat", "thelegging"], "imagelinks": ["https://scontent-icn1-1.cdninstagram.com/vp/78c32a85cf3104182e11e609852a396f/5CEB22F5/t51.2885-15/e35/50079442_574158696380092_535949936913061862_n.jpg?_nc_ht=scontent-icn1-1.cdninstagram.com"], "likes": "47", "comments": "18"}, {"id": "BtQbaeghR_9", "username": "click.n.pickk", "date": "2019-01-30T11:16:22", "hashtags": ["livelovelebanon", "fashion", "beirutcity", "beiruting", "winterfashion", "men", "livelovebeirut", "lebanese", "beirutfashion", "onlineshop", "shopnow", "womenfashion", "beirutsouks", "onlineboutique", "beirutshopping", "onlineshopping", "newcollection", "onlinestore", "lebaneseonline", "online", "dress", "lebanon", "lebanonstores", "shoes", "beirut", "heels", "lebanesefashion", "mensfashion", "lebanonshops", "women"], "imagelinks": ["https://scontent-icn1-1.cdninstagram.com/vp/f064b446decc2ab3f1f774beb1b41437/5CE6E973/t51.2885-15/e35/50247613_298832647491779_953758824817544009_n.jpg?_nc_ht=scontent-icn1-1.cdninstagram.com"], "likes": "8", "comments": "0"}, {"id": "BtQ7IOdnZMj", "username": "katha.rinah", "date": "2019-01-30T15:53:30", "hashtags": ["perfectday", "happiness", "photooftheday", "winterfashion", "girl", "love", "beautiful", "coldweather", "blackismyhappycolor", "enjoylife", "snowland", "snow", "winteroutfit", "winterwonderland", "wintertime"], "imagelinks": ["https://scontent-icn1-1.cdninstagram.com/vp/76f66bc0ab041ac5a2343228393953a7/5CF80861/t51.2885-15/e35/p1080x1080/50530005_508795169527251_846797586171772278_n.jpg?_nc_ht=scontent-icn1-1.cdninstagram.com"], "likes": "47", "comments": "1"}, {"id": "BtPASdiFh_K", "username": "lightinthebox", "date": "2019-01-29T22:00:07", "hashtags": ["outfitgoals", "thehappynow", "myunicornlife", "todayiamwearing", "winterfashion", "realoutfitgram", "fashionpost", "lookoftheday", "realoutfit", "livecolorfully", "stylefeed", "stylediares", "outfitinspiration", "fashionaddict", "flashesofdelight", "outfitideas", "fashionista", "mylook", "aboutalook", "outfitdaily", "ootd", "winteroutfit", "outfitgram", "pursuepretty", "springfashion", "mystyle", "springstyle", "streetstyle", "fashiongram", "nothingisordinary"], "imagelinks": ["https://scontent-icn1-1.cdninstagram.com/vp/be0370fbf3ae471d293d73eb9e3e0953/5CE60792/t51.2885-15/e35/49789586_2270343836512824_4725546578920826365_n.jpg?_nc_ht=scontent-icn1-1.cdninstagram.com"], "likes": "1425", "comments": "425Likes4"}, {"id": "BtQhDKIlH2D", "username": "marianne.ronnberg", "date": "2019-01-30T12:05:37", "hashtags": ["lapikkaat", "mywintershoes", "mysnowboots", "winteroutfit", "winterfashion"], "imagelinks": ["https://scontent-icn1-1.cdninstagram.com/vp/80a1fb0efb845d37429bde35171d6927/5CFA152E/t51.2885-15/e35/50576492_2031265423594343_1628786032364828446_n.jpg?_nc_ht=scontent-icn1-1.cdninstagram.com"], "likes": "51", "comments": "0"}, {"id": "BqM4SlJHQCB", "username": "rkhatsknits", "date": "2018-11-15T12:37:33", "hashtags": ["dog", "ootd", "like", "photography", "men", "fashionblogger", "love", "winteroutfit", "instagood", "snow", "model", "follow", "bhfyp", "christmas", "instafashion", "mensfashion", "winterfashion", "streetstyle", "winter", "style", "shopping", "photooftheday", "winterwonderland", "art", "fashion", "instagram", "me", "travel", "beauty", "winterstyle"], "imagelinks": ["https://scontent-icn1-1.cdninstagram.com/vp/4f88d88360338012e0ccd40cb883dc53/5CE08867/t51.2885-15/e35/44412301_360272274517483_650204616033471550_n.jpg?_nc_ht=scontent-icn1-1.cdninstagram.com"], "likes": "188", "comments": "25"}, {"id": "BtP7WVin3Z8", "username": "select_shop_gincho", "date": "2019-01-30T06:36:11", "hashtags": ["\u4e38\u4e80\u753a\u5546\u5e97\u8857", "mensstyle", "winterfashion", "mensshop", "selectshogincho", "gincho", "mensclothes", "\u4eca\u65e5\u306e\u5e97\u9577", "\u4eca\u65e5\u306e\u30b3\u30fc\u30c7\u30a3\u30cd\u30fc\u30c8", "\u30bb\u30ec\u30af\u30c8\u30b7\u30e7\u30c3\u30d7gincho", "\u3044\u3064\u3082\u306e\u4eca\u65e5\u306b\u304a\u3057\u3083\u308c\u3068\u3044\u3046\u697d\u3057\u307f\u3092", "\u4eca\u65e5\u306e\u30b3\u30fc\u30c7", "mensshopgincho", "\u597d\u304d\u306a\u670d\u3063\u3066\u3044\u3064\u3082\u306e\u4eca\u65e5\u3092\u304a\u3057\u3083\u308c\u306b\u5909\u3048\u308b", "winter", "mensapparel", "\u30e1\u30f3\u30ba\u30b7\u30e7\u30c3\u30d7\u30ae\u30f3\u30c1\u30e7\u30a6", "winterstyle", "mensfashion", "takamatsu", "kagawa", "newitem", "mens", "\u9ad8\u677e", "\u30e1\u30f3\u30ba\u30b7\u30e7\u30c3\u30d7gincho", "\u65b0\u4f5c", "menswear", "\u9999\u5ddd\u770c"], "imagelinks": ["https://scontent-icn1-1.cdninstagram.com/vp/2171e91d3b2f5a2c664764886626a9f0/5CF31344/t51.2885-15/e15/50773794_381313276004166_2221067635356750441_n.jpg?_nc_ht=scontent-icn1-1.cdninstagram.com"], "likes": "26", "comments": "2"}, {"id": "BtR9UhSBFum", "username": "kathrynspurr", "date": "2019-01-31T01:31:54", "hashtags": ["vancitystyle", "dailyhivestyle", "fashionover30", "ootdfashion", "fashioniver40", "myaritzia", "teacheroutfits", "effortlesschic", "outfitdiaries", "itsbanana", "fashiongram", "outfitinspo", "winterfashion", "fashioncanadians", "myeverydayedit", "teachersofinstagram", "plaidjacket", "whatiwear", "teacherfashion", "wiw", "wiwt", "metoday", "fashiondiaries", "casualstyle", "vancouverstyle", "igstyle", "whatiworetoday"], "imagelinks": ["https://scontent-icn1-1.cdninstagram.com/vp/e6c746cbb62c0a7a3b5353997c326ae0/5CE9BFFE/t51.2885-15/e35/50905694_254998935413221_2774818703512641119_n.jpg?_nc_ht=scontent-icn1-1.cdninstagram.com", "https://scontent-icn1-1.cdninstagram.com/vp/417dbb34c6779e85d78b29041cbfd669/5CE93F88/t51.2885-15/e35/50696548_600770747011748_4996309109589195994_n.jpg?_nc_ht=scontent-icn1-1.cdninstagram.com", "https://scontent-icn1-1.cdninstagram.com/vp/46bbab29fbbecc0c4c09d05b92c022ee/5CFF7888/t51.2885-15/e35/50061681_571338276718245_5360965706545069014_n.jpg?_nc_ht=scontent-icn1-1.cdninstagram.com", "https://scontent-icn1-1.cdninstagram.com/vp/a2cac8ae19f2cd6a56bf954a84e2fe91/5CF92BD2/t51.2885-15/e35/49648276_387044888510952_6448456023974277263_n.jpg?_nc_ht=scontent-icn1-1.cdninstagram.com", "https://scontent-icn1-1.cdninstagram.com/vp/2797b34fb65f998e8c28d5c3a102eb38/5CEF3641/t51.2885-15/e35/50874105_175473320082574_8314210764183771659_n.jpg?_nc_ht=scontent-icn1-1.cdninstagram.com", "https://scontent-icn1-1.cdninstagram.com/vp/47b7ad21ddd80c2a2daf5ec5dc5fdae7/5CE089B3/t51.2885-15/e35/50151556_2412539242307763_6883113509631123772_n.jpg?_nc_ht=scontent-icn1-1.cdninstagram.com"], "likes": "56", "comments": "4"}, {"id": "BtRzteinOCG", "username": "girtys_key", "date": "2019-01-31T00:07:55", "hashtags": ["beach", "winterfashion", "select", "girtyskey", "selectshop", "lifeisbeautiful", "fashion", "shichirigahama", "winter", "springcollection", "beachlife", "good"], "imagelinks": ["https://scontent-icn1-1.cdninstagram.com/vp/5a7b3b55aa4092535c885af5989667ca/5CF2EAC3/t51.2885-15/e35/50740919_116862279381338_5566242601060901233_n.jpg?_nc_ht=scontent-icn1-1.cdninstagram.com"], "likes": "43", "comments": "0"}, {"id": "BtSDWNjAIi6", "username": "weaningatlife", "date": "2019-01-31T02:24:33", "hashtags": ["brooklynbaby", "nyc", "momlife", "winterfashion", "parenting", "baby", "brooklyn"], "imagelinks": ["https://scontent-icn1-1.cdninstagram.com/vp/05951fd87bf29b9fb35b8c909e41c2f0/5CE6487D/t51.2885-15/e35/50477917_250467479211495_5577682071845862048_n.jpg?_nc_ht=scontent-icn1-1.cdninstagram.com"], "likes": "13", "comments": "1"}, {"id": "BtPcxtSgK1s", "username": "erasmovr", "date": "2019-01-30T02:09:03", "hashtags": ["photograph", "winter", "picoftheday", "photograpy", "photograper", "photos", "snowwhite", "photo", "bloggerstylefashion", "canada", "photograpic", "photomodel", "snowy", "photographers", "blogging", "snow", "bloggerlife", "winterlook", "blogger", "winterfashion", "bloggerstyle", "blogg"], "imagelinks": ["https://scontent-icn1-1.cdninstagram.com/vp/12d89d8fa318426a1ec941a8445be732/5CE11E79/t51.2885-15/e35/50623732_279820056032122_3508805580936516827_n.jpg?_nc_ht=scontent-icn1-1.cdninstagram.com"], "likes": "921", "comments": "8"}, {"id": "BtQ4_izHg4E", "username": "fashion_likesyou", "date": "2019-01-30T15:34:50", "hashtags": ["sandro", "fashionista", "kaiagerber", "nature", "fashionstyle", "pets", "chiaraferragni", "winterfashion", "fashionblogger", "helenabordon", "oliviapalermo", "winter", "thefashionguitar", "cindycrawford", "carodaur", "fashionblogg"], "imagelinks": ["https://scontent-icn1-1.cdninstagram.com/vp/803dbd4ab87a6cdf1bf0f0bf16247195/5CEAC1A3/t51.2885-15/e35/49956582_349541302554197_3652719710654908965_n.jpg?_nc_ht=scontent-icn1-1.cdninstagram.com"], "likes": "41", "comments": "4"}, {"id": "BtR6CWUhtnI", "username": "drjessicalynn", "date": "2019-01-31T01:03:12", "hashtags": ["nevergiveup", "loveyourself", "snow", "motivation", "womenrunning", "blessed", "noexcuses", "runner", "badazzrunners", "cold", "snowy", "snowyday", "running", "dedication", "athlete", "workhardplayhard", "winterfashion", "positivevibes", "womenempowerment", "keepgoing", "winterrunning", "beautiful"], "imagelinks": ["https://scontent-icn1-1.cdninstagram.com/vp/294326d0769919c3fb72ee0651e0ece8/5CF26D7C/t51.2885-15/e35/50201809_117095442691543_5085868211305750697_n.jpg?_nc_ht=scontent-icn1-1.cdninstagram.com"], "likes": "30", "comments": "1"}, {"id": "BtGc0I2jgPE", "username": "elina_andreus", "date": "2019-01-26T14:16:13", "hashtags": ["winterphotography", "\u0437\u0430\u043c\u0435\u0442\u0430\u0435\u0442", "likeforlikes", "winterwonderland", "winterfashion", "\u043f\u043e\u043c\u0435\u0440\u0437\u043b\u0438\u0438\u0445\u0432\u0430\u0442\u0438\u0442", "wintertime", "girl", "winter", "likelike", "\u0432\u0435\u0441\u043d\u0430\u043f\u0440\u0438\u0434\u0438"], "imagelinks": ["https://scontent-icn1-1.cdninstagram.com/vp/c7bfec0db12c93f7bf729330d68830ea/5CF183AA/t51.2885-15/e35/49388156_241578426790441_2079331898746816753_n.jpg?_nc_ht=scontent-icn1-1.cdninstagram.com"], "likes": "49", "comments": "1"}, {"id": "BtPut4GHpyJ", "username": "candyholladay", "date": "2019-01-30T04:45:48", "hashtags": [], "imagelinks": ["https://scontent-icn1-1.cdninstagram.com/vp/32f7e84ad931df04ba4e7d76bdf523ce/5D01247A/t51.2885-15/e35/50498156_2326935273993085_3380107670326651412_n.jpg?_nc_ht=scontent-icn1-1.cdninstagram.com"], "likes": "30", "comments": "6"}, {"id": "BtOy5Y7heug", "username": "flytrendzstl", "date": "2019-01-29T20:03:05", "hashtags": ["stlfashion", "menfashion", "stlmusic", "stlouis", "womenfashion", "risetogreatnessclothing", "hoodieseason", "stlartist", "flytrendzstl", "hoodie", "winterfashion", "ootd", "hiphop", "boutique", "dope", "clothes", "lotd", "stlouisgram", "joggingsuits", "stl", "stlboutique"], "imagelinks": ["https://scontent-icn1-1.cdninstagram.com/vp/1cf20a6f1ad37d66dd5138f5f513af4d/5CF45310/t51.2885-15/e35/50722799_153438475648041_8043102120012942297_n.jpg?_nc_ht=scontent-icn1-1.cdninstagram.com"], "likes": "47", "comments": "0"}, {"id": "BtRajpoH1RC", "username": "sheratonmke", "date": "2019-01-30T20:28:08", "hashtags": ["sheratonmke", "coldweather", "thecraftroommke", "babyitscoldoutside", "brookfield", "cold", "hotchocolate", "cheers", "winterfashion", "babyitscoldoutside\ufe0f", "mke", "hotellife", "winter", "travelblogger", "milwaukee", "wisconsin", "hotel", "travel", "yougotthis", "sheraton", "happy", "traveling"], "imagelinks": ["https://scontent-icn1-1.cdninstagram.com/vp/16b84eec592e05e9e730409721a5137b/5CF9B15E/t51.2885-15/e35/50175873_290349588278935_5058483534836870757_n.jpg?_nc_ht=scontent-icn1-1.cdninstagram.com", "https://scontent-icn1-1.cdninstagram.com/vp/48ea85712e06dd70fd3e8e2217669c18/5CFB0085/t51.2885-15/e35/50227291_339701319968976_7216674626760535605_n.jpg?_nc_ht=scontent-icn1-1.cdninstagram.com"], "likes": "25", "comments": "0"}, {"id": "BtSImOaHrFK", "username": "jism6", "date": "2019-01-31T03:10:26", "hashtags": ["gucciglasses", "likeforlike", "guccieyewear", "fashion", "winterfashion", "swagg", "dope", "nikeaf1", "mensfashion", "rickowensforever", "rickowens", "lfl", "chinatown", "knitwear", "blackoutfit", "comfy", "gucci", "cool", "fishermanbeanie", "barriochino", "rickowensmainline", "oversizedsweater", "cdmx", "style", "rickowensfw18", "allblackeverything", "mensstyle", "beanie"], "imagelinks": ["https://scontent-icn1-1.cdninstagram.com/vp/369e4440e31d595fe64c99502dc7bc07/5CE0F8AF/t51.2885-15/e35/49906816_600927290329319_1706295846795278363_n.jpg?_nc_ht=scontent-icn1-1.cdninstagram.com", "https://scontent-icn1-1.cdninstagram.com/vp/262f751ccfc39e2279d9ca0c12b78243/5CDFCFEF/t51.2885-15/e35/50984103_297755177610368_7116957982620567236_n.jpg?_nc_ht=scontent-icn1-1.cdninstagram.com", "https://scontent-icn1-1.cdninstagram.com/vp/153cf59df80e408ded3558ba128b08db/5CE29A88/t51.2885-15/e35/51152223_1668216906612915_951868942092021058_n.jpg?_nc_ht=scontent-icn1-1.cdninstagram.com", "https://scontent-icn1-1.cdninstagram.com/vp/68f051131575f9aea57b9ed9ed35828a/5CF51739/t51.2885-15/e35/49907388_538880433273327_7093109242786630402_n.jpg?_nc_ht=scontent-icn1-1.cdninstagram.com"], "likes": "49", "comments": "4"}, {"id": "BtO0bAdneKy", "username": "xhriss121", "date": "2019-01-29T20:16:25", "hashtags": ["winterfashion", "selfieoftheday", "mensphysique", "cozy", "menstyle", "instagay", "ootd", "badlighting", "coldoutside", "mensfashion", "gayboy", "comfy", "greenhair", "sweater", "gay", "style", "letsgo", "gayday", "outfit", "malefashion", "cuddleweather"], "imagelinks": ["https://scontent-icn1-1.cdninstagram.com/vp/57928ce1b15f3abdde1c5a9b2e803e28/5CE0B476/t51.2885-15/e35/50154926_2214337325483516_8686302708446477968_n.jpg?_nc_ht=scontent-icn1-1.cdninstagram.com"], "likes": "71", "comments": "3"}, {"id": "BtOlUKjhvY2", "username": "sainy_garg", "date": "2019-01-29T18:04:25", "hashtags": ["chubbygirl", "winteroutfit", "winterfashion", "fashionstyle", "winter", "likeforlikes", "puneinsta", "likeforfollow", "woolenberry", "creative", "cafe", "cap", "like4likes", "white"], "imagelinks": ["https://scontent-icn1-1.cdninstagram.com/vp/b016859035a82346bed7a6cf578e80b7/5CED8565/t51.2885-15/e35/50103981_296661241048806_2791431348012325279_n.jpg?_nc_ht=scontent-icn1-1.cdninstagram.com", "https://scontent-icn1-1.cdninstagram.com/vp/483bf71fdc8ed5f15631372f846ced2a/5CE4199C/t51.2885-15/e35/50643980_377796656112131_2087449589385879907_n.jpg?_nc_ht=scontent-icn1-1.cdninstagram.com"], "likes": "241", "comments": "15"}, {"id": "BtRjFUwlM-Z", "username": "svet_ka4119", "date": "2019-01-30T21:42:38", "hashtags": [], "imagelinks": ["https://scontent-icn1-1.cdninstagram.com/vp/5a513788caa5483497c9cd3cd546958b/5CF19805/t51.2885-15/e35/50834212_1146154722224522_611127437044217804_n.jpg?_nc_ht=scontent-icn1-1.cdninstagram.com", "https://scontent-icn1-1.cdninstagram.com/vp/a6cf09a0dbcb462867ed3ac80d38b286/5CF78BBE/t51.2885-15/e35/50107750_152991365696368_1667341011411375929_n.jpg?_nc_ht=scontent-icn1-1.cdninstagram.com"], "likes": "133", "comments": "22"}, {"id": "BtRndZShSVe", "username": "", "date": "2019-01-30T22:20:52", "hashtags": ["fashionart", "clothes", "sweaters", "style", "winterfashion", "clothesline", "winterstyle", "fashionarte", "photography", "clothesshopping"], "imagelinks": ["https://scontent-icn1-1.cdninstagram.com/vp/1db0ce3f28711b7de0d54e06b1a40bc7/5CFAB5B3/t51.2885-15/e35/50079461_112795569831792_5361113139292786667_n.jpg?_nc_ht=scontent-icn1-1.cdninstagram.com"], "likes": "22", "comments": "2"}]